<?xml version='1.0' encoding='UTF-8'?>
<text uploader="Adventures with Pinny" date="20231022" date_ts="1697983212" views="64295" title="Peru in 2 Weeks: Epic Adventure from Amazon to Machu Picchu" likes="1765" format="srv3" autocaption="true">
  <p time="80" is_ac="true">from the heart of the Amazon rainforest</p>
  <p time="2440" is_ac="true">to the ancient Ana Trail to Machu piku</p>
  <p time="5520" is_ac="true">in this video we will take you on our</p>
  <p time="7640" is_ac="true">two week adventure through kuu May it</p>
  <p time="11120" is_ac="true">Inspire your own epic journey to this</p>
  <p time="13519" is_ac="true">beautiful</p>
  <p time="15240" is_ac="true">[Music]</p>
  <p time="19039" is_ac="true">country after an 8 and 1/2 hour</p>
  <p time="22000" is_ac="true">overnight flight from LAX our journey</p>
  <p time="24960" is_ac="true">began in Peru's vibrant Capital Lima we</p>
  <p time="28359" is_ac="true">arrived at 7:30 a.m. M so obviously our</p>
  <p time="31599" is_ac="true">first priority was coffee and breakfast</p>
  <p time="34559" is_ac="true">makx it real</p>
  <p time="36840" is_ac="true">good first coffee of the trip tastes the</p>
  <p time="40120" is_ac="true">best we barely got any sleep on the</p>
  <p time="42399" is_ac="true">flight so it's</p>
  <p time="44399" is_ac="true">necessary with only one day in Lima</p>
  <p time="46879" is_ac="true">until the very end of our trip we fought</p>
  <p time="49399" is_ac="true">our jet lag and explored the upscale</p>
  <p time="51520" is_ac="true">neighborhood of Mira Flores where we</p>
  <p time="53640" is_ac="true">were staying the John F Kennedy Park</p>
  <p time="56879" is_ac="true">also known as the cat Park is a must for</p>
  <p time="59640" is_ac="true">cats lovers there were cats</p>
  <p time="62550" is_ac="true">[Music]</p>
  <p time="66439" is_ac="true">everywhere we also walked to the iconic</p>
  <p time="69360" is_ac="true">Love Park and admired the ocean</p>
  <p time="73000" is_ac="true">views after a quick break at our hotel</p>
  <p time="75720" is_ac="true">it was time to head out for dinner and</p>
  <p time="77600" is_ac="true">we had very exciting plans for dinner</p>
  <p time="79960" is_ac="true">that</p>
  <p time="81000" is_ac="true">night we had made reservations months in</p>
  <p time="84439" is_ac="true">advance to dine at Mido the number six</p>
  <p time="87799" is_ac="true">best restaurant in the world known for</p>
  <p time="89880" is_ac="true">for their Peruvian Japanese Fusion the</p>
  <p time="92320" is_ac="true">tasting menu included 11 courses and</p>
  <p time="95320" is_ac="true">each dish was better than the last our</p>
  <p time="98079" is_ac="true">personal favorite was the Toro fatty</p>
  <p time="100320" is_ac="true">tuna Bell niri that was prepared right</p>
  <p time="102840" is_ac="true">in front of us good thank you it was</p>
  <p time="106119" is_ac="true">seriously the best food I have ever</p>
  <p time="108620" is_ac="true">[Music]</p>
  <p time="112159" is_ac="true">eaten okay thanks to me happy birthday</p>
  <p time="115640" is_ac="true">to</p>
  <p time="121300" is_ac="true">[Music]</p>
  <p time="125399" is_ac="true">we got up bright and early for a 1 and</p>
  <p time="127920" is_ac="true">half hour flight from Lima to Puerto</p>
  <p time="130520" is_ac="true">Maldonado one of Peru's gateways to the</p>
  <p time="133239" is_ac="true">Amazon with one of the smallest airports</p>
  <p time="136280" is_ac="true">we have been to so</p>
  <p time="138480" is_ac="true">far after a stop at the rainforest</p>
  <p time="141400" is_ac="true">expedition's office we had a 1our drive</p>
  <p time="144400" is_ac="true">to the tambopata</p>
  <p time="146560" is_ac="true">River from there it was a 2 and 1/2 hour</p>
  <p time="149480" is_ac="true">boat ride to the Eco Lodge deep in the</p>
  <p time="152200" is_ac="true">heart of the Amazon rainforest and only</p>
  <p time="154720" is_ac="true">accessible by</p>
  <p time="156120" is_ac="true">boat along the way we even caught our</p>
  <p time="159120" is_ac="true">first glimpse of a capibara and a</p>
  <p time="170080" is_ac="true">Cayman for the next 4 days we would be</p>
  <p time="173159" is_ac="true">staying at the tambopata research center</p>
  <p time="176360" is_ac="true">the only Lodge located within the</p>
  <p time="178680" is_ac="true">tambopata nation National</p>
  <p time="181519" is_ac="true">Reserve looking for crits it's</p>
  <p time="183840" is_ac="true">allinclusive and the top rated EOD in</p>
  <p time="186760" is_ac="true">the area and with its location deep in</p>
  <p time="189280" is_ac="true">the jungle it has the highest chances of</p>
  <p time="191640" is_ac="true">seeing Wildlife such as monkeys and</p>
  <p time="194239" is_ac="true">maybe even a Jaguar fingers</p>
  <p time="197879" is_ac="true">crossed P.S I'll leave the links to all</p>
  <p time="200680" is_ac="true">of our hotels from this trip in the</p>
  <p time="202400" is_ac="true">description in case you're interested</p>
  <p time="204560" is_ac="true">our first</p>
  <p time="205760" is_ac="true">crit now we had the evening to do our</p>
  <p time="208439" is_ac="true">first trick Through the Jungle with our</p>
  <p time="210239" is_ac="true">own private</p>
  <p time="212040" is_ac="true">[Music]</p>
  <p time="216200" is_ac="true">guide we saw lots of creepy crawlers</p>
  <p time="219080" is_ac="true">including our first tarantula oh my</p>
  <p time="222680" is_ac="true">god wow it's kind of cute though right</p>
  <p time="226480" is_ac="true">wow it yeah it eyes are</p>
  <p time="229090" is_ac="true">[Music]</p>
  <p time="235200" is_ac="true">shining now we had three full days in</p>
  <p time="238280" is_ac="true">the Amazon rainforest</p>
  <p time="242239" is_ac="true">each day our private guide would take us</p>
  <p time="244319" is_ac="true">on Expeditions Through the Jungle</p>
  <p time="246400" is_ac="true">looking for wildlife definitely has a</p>
  <p time="248439" is_ac="true">suction to it feel like such an</p>
  <p time="251400" is_ac="true">adventurer don't fall in do we saw tons</p>
  <p time="254720" is_ac="true">of adorable monkeys Creepy Crawlers</p>
  <p time="257639" is_ac="true">colorful birds and so much</p>
  <p time="260959" is_ac="true">more but sadly no Jaguars we'll just</p>
  <p time="265000" is_ac="true">have to come back again</p>
  <p time="267840" is_ac="true">someday it was so learning about these</p>
  <p time="270759" is_ac="true">amazing creatures and seeing them in</p>
  <p time="272800" is_ac="true">their natural</p>
  <p time="277190" is_ac="true">[Music]</p>
  <p time="282520" is_ac="true">habitat one of our favorite parts of our</p>
  <p time="285039" is_ac="true">stay in the Amazon was visiting the MAA</p>
  <p time="287600" is_ac="true">clay we got there just after Sunrise as</p>
  <p time="291039" is_ac="true">hundreds of MAA gathered it was truly a</p>
  <p time="294360" is_ac="true">once- in a-lifetime</p>
  <p time="298560" is_ac="true">experience</p>
  <p time="305199" is_ac="true">if you want to see more of our time in</p>
  <p time="306880" is_ac="true">the Amazon and all of the amazing</p>
  <p time="309199" is_ac="true">creatures that we saw there make sure to</p>
  <p time="311600" is_ac="true">watch our full video exploring Peru's</p>
  <p time="314039" is_ac="true">Amazon rainforest I'll link it down</p>
  <p time="316440" is_ac="true">below but make sure to watch it after</p>
  <p time="318440" is_ac="true">this video of</p>
  <p time="321610" is_ac="true">[Music]</p>
  <p time="323520" is_ac="true">course wow oh that's</p>
  <p time="326440" is_ac="true">creepy he's so cute</p>
  <p time="330360" is_ac="true">sadly our time in the Amazon had come to</p>
  <p time="332720" is_ac="true">an end today we would be making the long</p>
  <p time="335360" is_ac="true">journey by boat and bus out of the</p>
  <p time="337880" is_ac="true">Amazon jungle back to Puerto Maldonado</p>
  <p time="341039" is_ac="true">adios</p>
  <p time="343290" is_ac="true">[Applause]</p>
  <p time="346170" is_ac="true">[Music]</p>
  <p time="352319" is_ac="true">jungle bye</p>
  <p time="354680" is_ac="true">am from Puerto Maldonado it was a 1 and</p>
  <p time="358039" is_ac="true">1/2 hour flight to Lima and then a 1 and</p>
  <p time="360759" is_ac="true">1/2 hour flight to Cusco exhausted from</p>
  <p time="363560" is_ac="true">a long travel day we checked into our</p>
  <p time="365680" is_ac="true">hotel in Cusco and pretty much went</p>
  <p time="368000" is_ac="true">straight to</p>
  <p time="369360" is_ac="true">bed now we had two full days in Cusco</p>
  <p time="373039" is_ac="true">our main goal was to acclimate to the</p>
  <p time="375039" is_ac="true">high altitude before we began hiking the</p>
  <p time="377240" is_ac="true">Inca Trail but we were excited to</p>
  <p time="379319" is_ac="true">explore the city not going to lie I was</p>
  <p time="381759" is_ac="true">definitely dealing with some altitude</p>
  <p time="383599" is_ac="true">sickness during this time but we powered</p>
  <p time="386319" is_ac="true">through it and made the most of our time</p>
  <p time="388400" is_ac="true">in stupid guy first we had booked a full</p>
  <p time="391800" is_ac="true">day tour from Cusco to explore the</p>
  <p time="393880" is_ac="true">nearby sacred Valley fun fact the Alpaca</p>
  <p time="397599" is_ac="true">Farm that we visited was at a higher</p>
  <p time="399680" is_ac="true">altitude than Cusco and I actually</p>
  <p time="402080" is_ac="true">fainted in their gift shop the workers</p>
  <p time="404520" is_ac="true">there were so nice and gave me this AGA</p>
  <p time="407120" is_ac="true">de Florida which apparently helps with</p>
  <p time="409160" is_ac="true">altitude sickness at least I feel like</p>
  <p time="411280" is_ac="true">it helped me PSA altitude sickness can</p>
  <p time="414120" is_ac="true">happen to anyone so be prepared and make</p>
  <p time="417160" is_ac="true">sure to give yourself time to acclimate</p>
  <p time="419120" is_ac="true">before before doing the Inca</p>
  <p time="421960" is_ac="true">Trail the rest of the tour we visited</p>
  <p time="424599" is_ac="true">some ruins and learned about the history</p>
  <p time="426759" is_ac="true">of the Sacred</p>
  <p time="428830" is_ac="true">[Music]</p>
  <p time="438520" is_ac="true">Valley on our second day in Cusco we</p>
  <p time="441479" is_ac="true">explored the</p>
  <p time="443840" is_ac="true">[Music]</p>
  <p time="448319" is_ac="true">city</p>
  <p time="451639" is_ac="true">the city was beautiful the food was</p>
  <p time="454120" is_ac="true">amazing and I can't wait to spend more</p>
  <p time="456440" is_ac="true">time here</p>
  <p time="458240" is_ac="true">someday to watch our full 2 Days in</p>
  <p time="460919" is_ac="true">Cusco check out our 48 hours in Cusco</p>
  <p time="463720" is_ac="true">video linked</p>
  <p time="464900" is_ac="true">[Music]</p>
  <p time="467440" is_ac="true">below the highlight of our entire trip</p>
  <p time="470360" is_ac="true">to Peru hiking the Inca</p>
  <p time="474520" is_ac="true">Trail no Peru Adventure itinerary is</p>
  <p time="477800" is_ac="true">complete without this bucket list</p>
  <p time="484159" is_ac="true">Journey however this hike is tough we</p>
  <p time="488400" is_ac="true">have just done our first incline and my</p>
  <p time="490840" is_ac="true">heart was pumping luckily they've been</p>
  <p time="492759" is_ac="true">taking a ton of breaks thank God</p>
  <p time="495479" is_ac="true">spanning 4 days 26 M with a total</p>
  <p time="499639" is_ac="true">elevation gain of over 7,000 ft reaching</p>
  <p time="503879" is_ac="true">a Max altitude of nearly</p>
  <p time="506800" is_ac="true">14,000 ft I'm pretty nervous for today</p>
  <p time="509960" is_ac="true">cuz it's the dead wilman's pass and all</p>
  <p time="513279" is_ac="true">a pill all day but it is well worth the</p>
  <p time="516599" is_ac="true">challenge after facing some altitude</p>
  <p time="519039" is_ac="true">sickness in Cusco I was especially</p>
  <p time="521680" is_ac="true">nervous but I found that while very</p>
  <p time="524480" is_ac="true">challenging taking it slow with plenty</p>
  <p time="526839" is_ac="true">of breaks made this hike totally doable</p>
  <p time="529399" is_ac="true">made it to dead woman's pass woohoo if I</p>
  <p time="532279" is_ac="true">can do it you can do it while we're</p>
  <p time="534640" is_ac="true">watching me fight for my life on the</p>
  <p time="536880" is_ac="true">Inca Trail feel pity for Lenny</p>
  <p time="539760" is_ac="true">and hit that like button and consider</p>
  <p time="541880" is_ac="true">subscribing for more adventures and bad</p>
  <p time="544820" is_ac="true">[Music]</p>
  <p time="549000" is_ac="true">jokes somebody roll me down this hill</p>
  <p time="551959" is_ac="true">across the 4 days of hiking we saw the</p>
  <p time="554480" is_ac="true">most beautiful views that we had ever</p>
  <p time="559399" is_ac="true">seen hiking the Inca Trail was the most</p>
  <p time="562760" is_ac="true">challenging thing that we had ever done</p>
  <p time="565440" is_ac="true">but we all agreed we would do it again</p>
  <p time="567320" is_ac="true">in a heartbeat oh oh holy</p>
  <p time="574920" is_ac="true">yeah after four grueling days of hiking</p>
  <p time="578640" is_ac="true">we made it to Machu piku we made it to</p>
  <p time="581440" is_ac="true">Machu</p>
  <p time="582839" is_ac="true">piku if you haven't seen it yet make</p>
  <p time="585399" is_ac="true">sure to watch our hiking the Inca Trail</p>
  <p time="587560" is_ac="true">video next it's probably my favorite</p>
  <p time="590279" is_ac="true">video that we've made so</p>
  <p time="593030" is_ac="true">[Music]</p>
  <p time="594920" is_ac="true">far hiking the Inca Trail was so</p>
  <p time="597760" is_ac="true">rewarding and I high highly recommend it</p>
  <p time="600000" is_ac="true">if you</p>
  <p time="600770" is_ac="true">[Music]</p>
  <p time="607250" is_ac="true">[Music]</p>
  <p time="623140" is_ac="true">[Music]</p>
  <p time="628040" is_ac="true">can back in Cusco we had some chill time</p>
  <p time="631079" is_ac="true">to rest up before heading back to</p>
  <p time="635720" is_ac="true">Lima it was an easy 1 and 1/2 hour</p>
  <p time="638600" is_ac="true">flight back from Cusco to</p>
  <p time="644440" is_ac="true">Lima we walked around the laramar</p>
  <p time="646959" is_ac="true">Cliffside shopping mall and got dinner</p>
  <p time="649000" is_ac="true">before heading to bed</p>
  <p time="650730" is_ac="true">[Music]</p>
  <p time="654480" is_ac="true">early it was our last day in Peru and we</p>
  <p time="657519" is_ac="true">finally had some time to explore FL Lima</p>
  <p time="660000" is_ac="true">so to make the most of it we booked a</p>
  <p time="661880" is_ac="true">full day tour of the city through get</p>
  <p time="663839" is_ac="true">your guide honestly I was really glad</p>
  <p time="666440" is_ac="true">that we booked this tour in order to see</p>
  <p time="668560" is_ac="true">and do as much as we could in Lima in</p>
  <p time="670920" is_ac="true">our short stay the tour took us to a</p>
  <p time="674040" is_ac="true">local</p>
  <p time="676600" is_ac="true">market to the ocean where we did a</p>
  <p time="679200" is_ac="true">cooking class which was delicious by the</p>
  <p time="684000" is_ac="true">way and then to downtown Lima where we</p>
  <p time="687200" is_ac="true">visited the catacombs learned about the</p>
  <p time="689480" is_ac="true">history of the city and admired the</p>
  <p time="692000" is_ac="true">vibrant buildings I'll leave a link in</p>
  <p time="694480" is_ac="true">the description below to the Lima tour</p>
  <p time="696519" is_ac="true">that we did in case you're interested</p>
  <p time="698959" is_ac="true">our trip to Peru was action-packed and</p>
  <p time="701440" is_ac="true">full of Epic Adventures from visiting</p>
  <p time="704040" is_ac="true">the Amazon rainforest to hiking the Inca</p>
  <p time="706600" is_ac="true">Trail and Crossing that off our bucket</p>
  <p time="708639" is_ac="true">list if you're ready to dive into more</p>
  <p time="711279" is_ac="true">detail of our Peru adventures and</p>
  <p time="713440" is_ac="true">prepare yourself for your own trip don't</p>
  <p time="715600" is_ac="true">forget to check out the other videos in</p>
  <p time="717639" is_ac="true">our Peru travel series thanks for</p>
  <p time="719839" is_ac="true">watching we'll see you next time we out</p>
  <p time="722959" is_ac="true">here we sleeping on the</p>
  <p time="725670" is_ac="true">[Music]</p>
  <p time="728480" is_ac="true">train top quality footage that was</p>
  <p time="731360" is_ac="true">terrible why did I do that weird</p>
  <p time="732959" is_ac="true">inflection but I found that what no I</p>
  <p time="735920" is_ac="true">need to stop saying B say it less</p>
  <p time="738839" is_ac="true">awkwardly okay just stop do it right</p>
  <p time="742399" is_ac="true">this time okay</p>
</text>
